CMakeLists.txt
LICENSE
MANIFEST.in
README.md
pyproject.toml
setup.py
iothpy/__init__.py
iothpy/const_linkadd.c
iothpy/iothpy.c
iothpy/iothpy_socket.c
iothpy/iothpy_socket.h
iothpy/iothpy_stack.c
iothpy/iothpy_stack.h
iothpy/msocket.py
iothpy/override.py
iothpy/stack.py
iothpy/utils.c
iothpy/utils.h
iothpy.egg-info/PKG-INFO
iothpy.egg-info/SOURCES.txt
iothpy.egg-info/dependency_links.txt
iothpy.egg-info/top_level.txt