Metadata-Version: 2.1
Name: iothpy
Version: 1.3.3
Summary: Python library for internet of threads
Home-page: https://github.com/ramenguy99/iothpy
Author: Dario Mylonopoulos
Author-email: dmylos@yahoo.it
Classifier: Operating System :: POSIX :: Linux
Requires-Python: >=3.6
License-File: LICENSE
